omito_config_plugin_env/__init__.py
omito_config_plugin_env-0.1.5.dist-info/WHEEL
omito_config_plugin_env-0.1.5.dist-info/METADATA
omito_config_plugin_env-0.1.5.dist-info/RECORD
